wax_toolbox/__init__.py
wax_toolbox/cli.py
wax_toolbox/misc_fixtures.py
wax_toolbox/profiling.py
wax_toolbox/tsanalytics.py
wax_toolbox-0.0.5.dist-info/METADATA
wax_toolbox-0.0.5.dist-info/RECORD
wax_toolbox-0.0.5.dist-info/WHEEL
wax_toolbox-0.0.5.dist-info/pbr.json
wax_toolbox-0.0.5.dist-info/top_level.txt
