Metadata-Version: 2.1
Name: wax-toolbox
Version: 0.0.5
Summary: Generic Python Tools
Home-page: https://github.com/gjeusel/wax-toolbox
Author: See AUTHORS
Author-email: "jeusel.guillaume@gmail.com"
License: UNKNOWN
Platform: UNKNOWN
Classifier: Development Status :: 4 - Beta
Classifier: Operating System :: MacOS :: MacOS X
Classifier: Operating System :: Microsoft :: Windows
Classifier: Operating System :: POSIX
Classifier: Programming Language :: Python
Classifier: Programming Language :: Python :: 3.6
Requires-Dist: pbr (>=3.0)
Requires-Dist: pyyaml
Requires-Dist: pandas
Requires-Dist: betamax
